[
  {
    "id": "aws-dva-development-1779896360471-0",
    "channel": "aws-dva",
    "subChannel": "development",
    "question": "Which DynamoDB feature uses an in-memory cache for microsecond reads?",
    "answer": "DynamoDB Accelerator (DAX)",
    "explanation": "DAX is an in-memory cache for DynamoDB providing microsecond read latency. Streams capture table changes. Global Tables handle multi-region replication.",
    "difficulty": "intermediate",
    "tags": [
      "dynamodb",
      "dax",
      "caching",
      "certification"
    ],
    "options": [
      {
        "id": "a",
        "text": "DynamoDB Accelerator (DAX)",
        "isCorrect": true
      },
      {
        "id": "b",
        "text": "DynamoDB Streams",
        "isCorrect": false
      },
      {
        "id": "c",
        "text": "Global Tables",
        "isCorrect": false
      },
      {
        "id": "d",
        "text": "Point-in-Time Recovery",
        "isCorrect": false
      }
    ],
    "status": "active",
    "lastUpdated": "2026-05-27T15:40:59.105Z"
  },
  {
    "id": "aws-dva-development-1779896360472-1",
    "channel": "aws-dva",
    "subChannel": "development",
    "question": "What is the primary purpose of a Lambda function alias?",
    "answer": "Point to a specific function version",
    "explanation": "Lambda aliases are pointers to a specific function version, enabling traffic shifting and stable deployment ARNs. Memory, VPC, and environment configs are set on the function itself.",
    "difficulty": "intermediate",
    "tags": [
      "lambda",
      "alias",
      "serverless",
      "certification"
    ],
    "options": [
      {
        "id": "a",
        "text": "Increase function memory limit",
        "isCorrect": false
      },
      {
        "id": "b",
        "text": "Point to a specific function version",
        "isCorrect": true
      },
      {
        "id": "c",
        "text": "Enable VPC network access",
        "isCorrect": false
      },
      {
        "id": "d",
        "text": "Configure environment variables",
        "isCorrect": false
      }
    ],
    "status": "active",
    "lastUpdated": "2026-05-27T15:40:59.106Z"
  }
]