{
  "$ref": "#/definitions/blog",
  "definitions": {
    "blog": {
      "type": "object",
      "properties": {
        "id": {
          "type": "string"
        },
        "title": {
          "type": "string"
        },
        "slug": {
          "type": "string"
        },
        "channel": {
          "type": "string"
        },
        "category": {
          "type": "string"
        },
        "difficulty": {
          "type": "string",
          "enum": [
            "beginner",
            "intermediate",
            "advanced"
          ]
        },
        "tags": {
          "type": "array",
          "items": {
            "type": "string"
          },
          "default": []
        },
        "createdAt": {
          "anyOf": [
            {
              "type": "string",
              "format": "date-time"
            },
            {
              "type": "string",
              "format": "date"
            },
            {
              "type": "integer",
              "format": "unix-time"
            }
          ]
        },
        "publishedAt": {
          "anyOf": [
            {
              "type": "string",
              "format": "date-time"
            },
            {
              "type": "string",
              "format": "date"
            },
            {
              "type": "integer",
              "format": "unix-time"
            }
          ]
        },
        "funFact": {
          "type": "string"
        },
        "diagram": {
          "type": "string"
        },
        "images": {
          "type": "array",
          "items": {
            "type": "object",
            "properties": {
              "url": {
                "type": "string"
              },
              "alt": {
                "type": "string",
                "default": ""
              },
              "caption": {
                "type": "string",
                "default": ""
              },
              "placement": {
                "type": "string",
                "default": ""
              }
            },
            "required": [
              "url"
            ],
            "additionalProperties": false
          },
          "default": []
        },
        "sources": {
          "type": "array",
          "items": {
            "type": "object",
            "properties": {
              "title": {
                "type": "string"
              },
              "url": {
                "type": "string"
              },
              "type": {
                "type": "string",
                "default": "article"
              }
            },
            "required": [
              "title",
              "url"
            ],
            "additionalProperties": false
          },
          "default": []
        },
        "author": {
          "type": "string"
        },
        "coverImage": {
          "type": "string"
        },
        "excerpt": {
          "type": "string"
        },
        "featured": {
          "type": "boolean",
          "default": false
        },
        "readingTimeMinutes": {
          "type": "number"
        }
      },
      "required": [
        "title",
        "slug"
      ],
      "additionalProperties": false
    }
  },
  "$schema": "http://json-schema.org/draft-07/schema#"
}